odoo/addons/shopfloor_manual_product_transfer/README.rst
odoo/addons/shopfloor_manual_product_transfer/__init__.py
odoo/addons/shopfloor_manual_product_transfer/__manifest__.py
odoo/addons/shopfloor_manual_product_transfer/hooks.py
odoo/addons/shopfloor_manual_product_transfer/actions/__init__.py
odoo/addons/shopfloor_manual_product_transfer/actions/message.py
odoo/addons/shopfloor_manual_product_transfer/data/shopfloor_scenario.xml
odoo/addons/shopfloor_manual_product_transfer/demo/shopfloor_menu.xml
odoo/addons/shopfloor_manual_product_transfer/demo/stock_picking_type.xml
odoo/addons/shopfloor_manual_product_transfer/docs/manual_product_transfer_diag_seq.plantuml
odoo/addons/shopfloor_manual_product_transfer/docs/manual_product_transfer_diag_seq.png
odoo/addons/shopfloor_manual_product_transfer/i18n/pt_BR.po
odoo/addons/shopfloor_manual_product_transfer/i18n/shopfloor_manual_product_transfer.pot
odoo/addons/shopfloor_manual_product_transfer/readme/CONTRIBUTORS.rst
odoo/addons/shopfloor_manual_product_transfer/readme/CREDITS.rst
odoo/addons/shopfloor_manual_product_transfer/readme/DESCRIPTION.rst
odoo/addons/shopfloor_manual_product_transfer/services/__init__.py
odoo/addons/shopfloor_manual_product_transfer/services/manual_product_transfer.py
odoo/addons/shopfloor_manual_product_transfer/static/description/icon.png
odoo/addons/shopfloor_manual_product_transfer/static/description/index.html
odoo/addons/shopfloor_manual_product_transfer/tests/__init__.py
odoo/addons/shopfloor_manual_product_transfer/tests/test_manual_product_transfer_base.py
odoo/addons/shopfloor_manual_product_transfer/tests/test_manual_product_transfer_confirm_quantity.py
odoo/addons/shopfloor_manual_product_transfer/tests/test_manual_product_transfer_misc.py
odoo/addons/shopfloor_manual_product_transfer/tests/test_manual_product_transfer_scan_destination_location.py
odoo/addons/shopfloor_manual_product_transfer/tests/test_manual_product_transfer_scan_product.py
odoo14_addon_shopfloor_manual_product_transfer-14.0.1.5.1.dist-info/METADATA
odoo14_addon_shopfloor_manual_product_transfer-14.0.1.5.1.dist-info/WHEEL
odoo14_addon_shopfloor_manual_product_transfer-14.0.1.5.1.dist-info/top_level.txt
odoo14_addon_shopfloor_manual_product_transfer-14.0.1.5.1.dist-info/RECORD
